py21cmfast_tools/__init__.py
py21cmfast_tools/lc2ps.py
py21cmfast_tools-1.0.4.dist-info/LICENSE
py21cmfast_tools-1.0.4.dist-info/METADATA
py21cmfast_tools-1.0.4.dist-info/WHEEL
py21cmfast_tools-1.0.4.dist-info/top_level.txt
py21cmfast_tools-1.0.4.dist-info/RECORD
